scripts/__init__.py
scripts/api.py
scripts/downloader.py
ytp_dl-0.6.3.dist-info/METADATA
ytp_dl-0.6.3.dist-info/WHEEL
ytp_dl-0.6.3.dist-info/entry_points.txt
ytp_dl-0.6.3.dist-info/top_level.txt
ytp_dl-0.6.3.dist-info/RECORD
