Metadata-Version: 2.2
Name: ytp-dl
Version: 0.6.3
Summary: YouTube video downloader with Mullvad VPN integration and Flask API
Home-page: https://github.com/yourusername/ytp-dl
Author: dumgum82
Author-email: dumgum42@gmail.com
Classifier: Programming Language :: Python :: 3
Classifier: License :: OSI Approved :: MIT License
Classifier: Operating System :: POSIX :: Linux
Classifier: Topic :: Internet :: WWW/HTTP
Classifier: Topic :: Multimedia :: Video
Classifier: Topic :: Utilities
Classifier: Programming Language :: Python :: 3.8
Classifier: Programming Language :: Python :: 3.9
Classifier: Programming Language :: Python :: 3.10
Classifier: Programming Language :: Python :: 3.11
Requires-Python: >=3.8
Requires-Dist: yt-dlp[default]
Requires-Dist: flask
Requires-Dist: requests
Requires-Dist: gevent
Requires-Dist: gunicorn
Dynamic: author
Dynamic: author-email
Dynamic: classifier
Dynamic: description
Dynamic: description-content-type
Dynamic: home-page
Dynamic: requires-dist
Dynamic: requires-python
Dynamic: summary
